{
  "document_role": "scoped_current_audit_not_package_wide_truth_source",
  "current_truth_source": false,
  "truth_scope": "scoped_current_audit",
  "canonical_current_state_chain": "docs/review/conformance/current_state_chain.current.json",
  "documentation_truth_reviewed_at": "2026-03-26",
  "scoped_audit_scope": "focused_current_rfc_applicability_support_snapshot",
  "not_package_wide_truth_source": true,
  "checkpoint": "phase8_rfc_applicability_competitor_support_update",
  "reviewed_on": "2026-03-26",
  "summary": {
    "core_applicable_rfcs_from_user_table": [
      "rfc9112",
      "rfc9113",
      "rfc9114",
      "rfc9110_bounded",
      "rfc7232",
      "rfc7233",
      "rfc8297",
      "rfc7838_section3"
    ],
    "adjacent_optional_expansion_rfcs": [
      "rfc9530"
    ],
    "separate_boundary_optional_rfcs": [
      "rfc7515",
      "rfc7516",
      "rfc7519",
      "rfc8152",
      "rfc9052"
    ],
    "first_priority_is_strict_current_target_closure": true,
    "notes": [
      "tigrcorn is strongest today as a transport/server RFC implementation with direct entity semantics and direct-delivery support rather than a JOSE/COSE or caching platform",
      "the current boundary now also includes RFC 8297 and the bounded RFC 7838 \u00a73 Alt-Svc header-field profile",
      "RFC 9530, RFC 9111, and RFC 9421 remain optional future expansions rather than current direct-server obligations",
      "RFC 9218 remains transport-adjacent optional work and is not yet targeted"
    ],
    "conditional_boundary_expansion_rfcs": [
      "rfc9111",
      "rfc9421"
    ],
    "transport_adjacent_optional_rfcs": [
      "rfc9218"
    ]
  },
  "applicability": {
    "rfc9112": {
      "applicability": "core_transport",
      "current_state": "targeted_and_independently_certified",
      "recommended_posture": "keep_core"
    },
    "rfc9113": {
      "applicability": "core_transport",
      "current_state": "targeted_and_independently_certified",
      "recommended_posture": "keep_core"
    },
    "rfc9114": {
      "applicability": "core_transport",
      "current_state": "targeted_and_independently_certified",
      "recommended_posture": "keep_core"
    },
    "rfc9110": {
      "applicability": "core_but_bounded",
      "current_state": "targeted_only_for_connect_trailers_and_content_coding",
      "recommended_posture": "keep_bounded_until_boundary_expands"
    },
    "rfc7232": {
      "applicability": "core_entity_semantics",
      "current_state": "targeted_and_release_gated_local_conformance",
      "recommended_posture": "keep_core_entity_semantics"
    },
    "rfc7233": {
      "applicability": "core_entity_semantics",
      "current_state": "targeted_and_release_gated_local_conformance",
      "recommended_posture": "keep_core_entity_semantics"
    },
    "rfc9111": {
      "applicability": "conditional_expansion",
      "current_state": "not_targeted",
      "recommended_posture": "add_only_if_cache_revalidation_semantics_are_deliberately_adopted"
    },
    "rfc9530": {
      "applicability": "adjacent_expansion",
      "current_state": "not_targeted",
      "recommended_posture": "add_if_digest_fields_become_product_requirements"
    },
    "rfc9421": {
      "applicability": "conditional_expansion",
      "current_state": "not_targeted",
      "recommended_posture": "add_only_if_signed_http_message_handling_becomes_a_product_goal"
    },
    "rfc7515": {
      "applicability": "separate_auth_crypto_boundary",
      "current_state": "not_targeted",
      "recommended_posture": "keep_optional"
    },
    "rfc7516": {
      "applicability": "separate_auth_crypto_boundary",
      "current_state": "not_targeted",
      "recommended_posture": "keep_optional"
    },
    "rfc7519": {
      "applicability": "separate_auth_crypto_boundary",
      "current_state": "not_targeted",
      "recommended_posture": "keep_optional"
    },
    "rfc8152": {
      "applicability": "separate_binary_envelope_boundary",
      "current_state": "not_targeted",
      "recommended_posture": "keep_optional"
    },
    "rfc9052": {
      "applicability": "separate_binary_envelope_boundary",
      "current_state": "not_targeted",
      "recommended_posture": "keep_optional"
    },
    "rfc8297": {
      "applicability": "core_direct_delivery",
      "current_state": "targeted_and_release_gated_local_conformance",
      "recommended_posture": "keep_core_direct_delivery"
    },
    "rfc7838": {
      "applicability": "core_but_bounded_header_field_profile",
      "current_state": "targeted_and_release_gated_local_conformance",
      "recommended_posture": "keep_bounded_until_protocol_level_alt_svc_is_explicitly_adopted"
    },
    "rfc9218": {
      "applicability": "transport_adjacent_optional",
      "current_state": "not_targeted",
      "recommended_posture": "keep_outside_current_boundary_until_explicit_prioritization_semantics_are_adopted"
    }
  },
  "recommended_next_work": {
    "strict_current_target_closure": [
      "keep the current authoritative / strict / promotion model green",
      "keep preserved artifacts, release-gate truth, and machine-readable current-state docs synchronized"
    ],
    "boundary_expansion_after_strict_closure": [
      "formalize rfc7232 conditional request subsystem as current boundary work (completed)",
      "formalize rfc7233 range request subsystem as current boundary work (completed)",
      "implement rfc9530 content_digest and repr_digest only if integrity fields become a declared product requirement",
      "implement rfc9111 origin-side cache and freshness behavior only if cache-aware behavior becomes a deliberate product goal",
      "implement rfc9421 http message signatures only if signed edge or gateway behavior becomes a deliberate product goal",
      "implement rfc9651 structured fields as a supporting dependency only if digest/signature work is adopted"
    ],
    "keep_optional_unless_boundary_changes": [
      "rfc7515",
      "rfc7516",
      "rfc7519",
      "rfc8152",
      "rfc9052"
    ]
  },
  "public_competitor_support": {
    "tigrcorn": {
      "http1": "yes",
      "http2": "yes",
      "http3": "yes",
      "bounded_rfc9110_target": "yes",
      "rfc7232_rfc7233_first_class_server_feature": "yes",
      "rfc9111_rfc9530_rfc9421_first_class_server_feature": "no",
      "notes": "transport-centric RFC program with deeper H3/QUIC posture than the reviewed competitors and direct entity-semantic support for validators and byte ranges"
    },
    "uvicorn": {
      "http1": "yes",
      "http2": "no_public_current_claim",
      "http3": "no_public_current_claim",
      "websocket": "yes",
      "reload": "yes",
      "workers": "yes",
      "permessage_deflate": "yes",
      "notes": "strong CLI/operator surface, but current official docs only market HTTP/1.1 and WebSockets"
    },
    "hypercorn": {
      "http1": "yes",
      "http2": "yes",
      "http3": "optional_draft_via_aioquic",
      "websocket": "yes_over_http1_and_http2",
      "config_files": "yes",
      "workers": "yes",
      "statsd": "yes",
      "notes": "broad server surface and tuning/config features; public docs are less explicit than tigrcorn on H3 certification depth"
    },
    "daphne": {
      "http1": "yes",
      "http2": "yes",
      "http3": "no_public_current_claim",
      "websocket": "yes",
      "fd_and_endpoint_strings": "yes",
      "notes": "solid HTTP/2/WebSocket server positioning with Twisted endpoint flexibility, but much narrower documented tuning surface"
    },
    "granian": {
      "http1": "yes",
      "http2": "yes",
      "http3": "future_direction_not_current_support",
      "websocket": "yes",
      "mtls": "yes",
      "runtime_tuning": "yes",
      "notes": "very strong runtime and throughput-oriented surface; current public docs say HTTP/3 is eventual rather than current"
    }
  },
  "notes": {
    "authoritative_answer_alignment": "This machine-readable snapshot aligns with RFC_APPLICABILITY_AND_COMPETITOR_SUPPORT.md: RFC 7232 / RFC 7233 remain current package-boundary entity semantics, RFC 8297 and the bounded RFC 7838 \u00a73 profile are now current package-boundary direct-delivery semantics, RFC 9218 remains transport-adjacent optional work, and RFC 9530 / RFC 9111 / RFC 9421 remain optional future expansions."
  },
  "roadmap": {
    "keep_boundary_green_and_honest": [
      "rfc7232",
      "rfc7233",
      "rfc8297",
      "rfc7838"
    ],
    "keep_current_local_only_surfaces_aligned": [
      "rfc7692",
      "rfc9110_connect",
      "rfc9110_trailers",
      "rfc9110_content_coding",
      "rfc6960"
    ],
    "if_boundary_expands_next": [
      "rfc9530"
    ],
    "if_prioritization_is_adopted": [
      "rfc9218"
    ],
    "if_boundary_expands_into_cache_or_integrity": [
      "rfc9111",
      "rfc9421",
      "rfc9651"
    ],
    "keep_optional_unless_boundary_changes": [
      "rfc7515",
      "rfc7516",
      "rfc7519",
      "rfc8152",
      "rfc9052"
    ]
  }
}
